{
    "swagger": "2.0",
    "info": {
        "contact": {},
        "license": {
            "name": "MIT",
            "url": "https://github.com/simple-retro/api/blob/master/LICENSE"
        }
    },
    "paths": {
        "/health": {
            "get": {
                "consumes": [
                    "application/json"
                ],
                "produces": [
                    "application/json"
                ],
                "tags": [
                    ""
                ],
                "summary": "Show API health",
                "responses": {
                    "200": {
                        "description": "API metrics",
                        "schema": {
                            "$ref": "#/definitions/server.health"
                        }
                    },
                    "500": {
                        "description": "Internal error",
                        "schema": {
                            "type": "string"
                        }
                    }
                }
            }
        }
    },
    "definitions": {
        "server.health": {
            "type": "object",
            "properties": {
                "cpu": {
                    "type": "number"
                },
                "memory": {
                    "type": "number"
                },
                "name": {
                    "type": "string"
                }
            }
        }
    }
}